{"text": "The Amazing Spiderman", "choice_text": null, "path": [{"text": "Spiderman to the rescue!", "choice_text": "Spiderman to rescue", "path": [{"text": "Spiderman go sleep", "choice_text": "Spiderman go to sleep", "path": []}, {"text": "Spiderman to the rescue", "choice_text": "Spiderman continue rescue", "path": [{"text": "spiderman go rescue man", "choice_text": "Spiderman rescue man", "path": []}, {"text": "spiderman go stop robbery", "choice_text": "Spiderman stop robbery", "path": []}]}]}]}